{
  "storyId": "BACKUP-007",
  "title": "Execute backup validation",
  "description": "As a system admin, I want to run backup integrity tests so that data recovery is guaranteed.",
  "asA": "system admin",
  "iWant": "to run backup integrity tests",
  "soThat": "data recovery is guaranteed",
  "acceptanceCriteria": [
    "Backup files are verified for completeness",
    "Restore process completes successfully",
    "Data integrity checks pass validation",
    "Recovery time meets RTO requirements"
  ],
  "enhanced": true,
  "components": ["Run_Verify"],
  "storyPoint": 5,
  "assigneeEmail": "sysadmin@example.com",
  "status": "Ready",
  "acceptWarnings": true
}
